cm2mem_gsq/__init__.py
cm2mem_gsq/cm2mem.py
cm2mem_gsq-0.0.1.dist-info/LICENSE
cm2mem_gsq-0.0.1.dist-info/METADATA
cm2mem_gsq-0.0.1.dist-info/WHEEL
cm2mem_gsq-0.0.1.dist-info/top_level.txt
cm2mem_gsq-0.0.1.dist-info/RECORD
