Metadata-Version: 2.1
Name: cm2mem-gsq
Version: 0.0.1
Summary: Allows easy manipulation of memory in the Roblox game Circuit Maker 2. Supports MassiveMemory and MassMemory.
Author-email: Gogle Squirminton <goglesquirmintontheiii@gmail.com>
Classifier: Programming Language :: Python :: 3
Classifier: License :: OSI Approved :: MIT License
Classifier: Operating System :: OS Independent
Requires-Python: >=3.8
License-File: LICENSE
